dyagram/__init__.py
dyagram/dyagram.py
dyagram/cli/__init__.py
dyagram/cli/dyagram.py
dyagram/cli/export.py
dyagram/cli/initialize.py
dyagram/cli/sites.py
dyagram/initialize/__init__.py
dyagram/initialize/initialize.py
dyagram/sites/__init__.py
dyagram/sites/sites.py
dyagram-0.0.211.dist-info/METADATA
dyagram-0.0.211.dist-info/WHEEL
dyagram-0.0.211.dist-info/entry_points.txt
dyagram-0.0.211.dist-info/top_level.txt
dyagram-0.0.211.dist-info/RECORD
