Metadata-Version: 2.1
Name: dyagram
Version: 0.0.211
Summary: Agentless IaC Tool to map out the state of your network
Home-page: UNKNOWN
Author: Chris Moses
Author-email: chrismoses121@gmail.com
License: UNKNOWN
Platform: UNKNOWN
Requires-Dist: bcrypt (==4.0.1)
Requires-Dist: cffi (==1.15.1)
Requires-Dist: cryptography (==39.0.1)
Requires-Dist: deepdiff (==6.3.0)
Requires-Dist: diagrams (==0.23.3)
Requires-Dist: future (==0.18.3)
Requires-Dist: netmiko (==4.1.2)
Requires-Dist: ntc-templates (==3.2.0)
Requires-Dist: paramiko (==3.0.0)
Requires-Dist: pycparser (==2.21)
Requires-Dist: PyNaCl (==1.5.0)
Requires-Dist: pyserial (==3.5)
Requires-Dist: pywin32 (==305)
Requires-Dist: PyYAML (==6.0)
Requires-Dist: requests (==2.28.2)
Requires-Dist: scp (==0.14.5)
Requires-Dist: six (==1.16.0)
Requires-Dist: tenacity (==8.2.1)
Requires-Dist: textfsm (==1.1.2)
